ascii_animator/__init__.py
ascii_animator/animator.py
ascii_animator/cli.py
ascii_animator-0.2.1.dist-info/METADATA
ascii_animator-0.2.1.dist-info/WHEEL
ascii_animator-0.2.1.dist-info/entry_points.txt
ascii_animator-0.2.1.dist-info/namespace_packages.txt
ascii_animator-0.2.1.dist-info/top_level.txt
ascii_animator-0.2.1.dist-info/zip-safe
ascii_animator-0.2.1.dist-info/RECORD
