Metadata-Version: 2.1
Name: ascii-animator
Version: 0.2.1
Summary: A simple ASCII art animator
Home-page: https://github.com/soda480/ascii-animator
Author: Emilio Reyes
Author-email: soda480@gmail.com
Maintainer: 
Maintainer-email: 
License: Apache License, Version 2.0
Classifier: Programming Language :: Python
Classifier: Programming Language :: Python :: 3.8
Classifier: Programming Language :: Python :: 3.9
Classifier: Programming Language :: Python :: 3.10
Classifier: Programming Language :: Python :: 3.11
Classifier: Programming Language :: Python :: 3.12
Requires-Dist: list2term~=0.1.0
Requires-Dist: ascii-magic~=1.6
